{"cameraMode":{"drawMode":0,"name":"Shaded","section":"Shading Mode"},"sceneLighting":true,"audioPlay":false,"sceneViewState":{"m_AlwaysRefresh":false,"showFog":true,"showSkybox":true,"showFlares":true,"showImageEffects":true,"showParticleSystems":true,"showVisualEffectGraphs":true,"m_FxEnabled":true},"in2DMode":false,"pivot":{"x":-8.123244285583496,"y":3.518475294113159,"z":-10.4374418258667},"rotation":{"x":-0.28215712308883669,"y":0.37112924456596377,"z":-0.11946787685155869,"w":-0.8765947222709656},"size":3.5028481483459474,"orthographic":false}